{
    "11411": {
        "company_cd": 3,
        "line_name": "JR中央本線(名古屋～塩尻)"
    },
    "11416": {
        "company_cd": 3,
        "line_name": "JR高山本線"
    },
    "11502": {
        "company_cd": 3,
        "line_name": "JR東海道本線(浜松～岐阜)"
    },
    "11503": {
        "company_cd": 3,
        "line_name": "JR東海道本線(岐阜～美濃赤坂・米原)"
    },
    "11507": {
        "company_cd": 3,
        "line_name": "JR太多線"
    },
    "30001": {
        "company_cd": 20,
        "line_name": "名鉄名古屋本線"
    },
    "30015": {
        "company_cd": 20,
        "line_name": "名鉄犬山線"
    },
    "30016": {
        "company_cd": 20,
        "line_name": "名鉄各務原線"
    },
    "30017": {
        "company_cd": 20,
        "line_name": "名鉄広見線"
    },
    "30020": {
        "company_cd": 20,
        "line_name": "名鉄竹鼻線"
    },
    "30021": {
        "company_cd": 20,
        "line_name": "名鉄羽島線"
    },
    "31004": {
        "company_cd": 21,
        "line_name": "近鉄養老線"
    },
    "99411": {
        "company_cd": 161,
        "line_name": "神岡鉄道神岡線"
    },
    "99524": {
        "company_cd": 183,
        "line_name": "明知鉄道明知線"
    },
    "99525": {
        "company_cd": 184,
        "line_name": "長良川鉄道越美南線"
    },
    "99526": {
        "company_cd": 185,
        "line_name": "樽見鉄道樽見線"
    },
    "99532": {
        "company_cd": 189,
        "line_name": "養老鉄道養老線"
    }
}