[
    {
        "code": "B101252000010",
        "type": 16001,
        "name": "幌延小学校",
        "address": "天塩郡幌延町東町25",
        "lat": 45.014495,
        "lng": 141.854764
    },
    {
        "code": "B101252000029",
        "type": 16001,
        "name": "問寒別小学校",
        "address": "天塩郡幌延町字問寒別130",
        "lat": 44.91654,
        "lng": 142.021809
    },
    {
        "code": "C101252000018",
        "type": 16002,
        "name": "幌延中学校",
        "address": "天塩郡幌延町字幌延102",
        "lat": 45.022382,
        "lng": 141.844709
    },
    {
        "code": "C101252000027",
        "type": 16002,
        "name": "問寒別中学校",
        "address": "天塩郡幌延町字問寒別130",
        "lat": 44.916151,
        "lng": 142.021421
    }
]