[
    {
        "code": "A216332276011",
        "type": 16013,
        "name": "宮川こども園",
        "address": "中新川郡上市町中江上96",
        "lat": 36.719344,
        "lng": 137.3498
    },
    {
        "code": "A216332276020",
        "type": 16013,
        "name": "相ノ木保育園",
        "address": "中新川郡上市町飯坂新125-1",
        "lat": 36.715905,
        "lng": 137.328516
    },
    {
        "code": "B116232200013",
        "type": 16001,
        "name": "相ノ木小学校",
        "address": "中新川郡上市町上荒又68",
        "lat": 36.712109,
        "lng": 137.330996
    },
    {
        "code": "B116232200022",
        "type": 16001,
        "name": "上市中央小学校",
        "address": "中新川郡上市町横法音寺1",
        "lat": 36.700527,
        "lng": 137.363216
    },
    {
        "code": "B116232200031",
        "type": 16001,
        "name": "南加積小学校",
        "address": "中新川郡上市町広野768",
        "lat": 36.712693,
        "lng": 137.377464
    },
    {
        "code": "B116232200040",
        "type": 16001,
        "name": "宮川小学校",
        "address": "中新川郡上市町中江上2",
        "lat": 36.716831,
        "lng": 137.353994
    },
    {
        "code": "B116232200059",
        "type": 16001,
        "name": "白萩西部小学校",
        "address": "中新川郡上市町丸山43",
        "lat": 36.693695,
        "lng": 137.380909
    },
    {
        "code": "B116232200068",
        "type": 16001,
        "name": "陽南小学校",
        "address": "中新川郡上市町柿沢424-2",
        "lat": 36.681862,
        "lng": 137.364244
    },
    {
        "code": "B116232200077",
        "type": 16001,
        "name": "白萩南部小学校",
        "address": "中新川郡上市町東種17",
        "lat": 36.67028,
        "lng": 137.424347
    },
    {
        "code": "C116232230015",
        "type": 16002,
        "name": "上市中学校",
        "address": "中新川郡上市町稗田1",
        "lat": 36.695167,
        "lng": 137.362133
    },
    {
        "code": "D116232250018",
        "type": 16004,
        "name": "上市高等学校",
        "address": "中新川郡上市町斉神新444",
        "lat": 36.70636,
        "lng": 137.369993
    }
]