[
    {
        "code": "A122210000024",
        "type": 16011,
        "name": "伊豆山幼稚園",
        "address": "熱海市伊豆山711",
        "lat": 35.115911,
        "lng": 139.083915
    },
    {
        "code": "A122210000042",
        "type": 16011,
        "name": "多賀幼稚園",
        "address": "熱海市下多賀918-1",
        "lat": 35.04976,
        "lng": 139.069737
    },
    {
        "code": "A122210000051",
        "type": 16011,
        "name": "泉幼稚園",
        "address": "熱海市泉52-1",
        "lat": 35.143021,
        "lng": 139.076736
    },
    {
        "code": "A122310000139",
        "type": 16011,
        "name": "熱海幼稚園",
        "address": "熱海市上宿町7-28",
        "lat": 35.097083,
        "lng": 139.070622
    },
    {
        "code": "A222210000808",
        "type": 16013,
        "name": "あたみこども園",
        "address": "熱海市桜町3-20",
        "lat": 35.088899,
        "lng": 139.067807
    },
    {
        "code": "B122210000219",
        "type": 16001,
        "name": "第一小学校",
        "address": "熱海市西山町41-1",
        "lat": 35.1016,
        "lng": 139.067179
    },
    {
        "code": "B122210000228",
        "type": 16001,
        "name": "初島小学校",
        "address": "熱海市初島219",
        "lat": 35.042129,
        "lng": 139.170755
    },
    {
        "code": "B122210000237",
        "type": 16001,
        "name": "第二小学校",
        "address": "熱海市桜町3-20",
        "lat": 35.088879,
        "lng": 139.067707
    },
    {
        "code": "B122210000246",
        "type": 16001,
        "name": "多賀小学校",
        "address": "熱海市下多賀920-1",
        "lat": 35.048996,
        "lng": 139.069568
    },
    {
        "code": "B122210000255",
        "type": 16001,
        "name": "伊豆山小学校",
        "address": "熱海市伊豆山711",
        "lat": 35.115794,
        "lng": 139.083661
    },
    {
        "code": "B122210000264",
        "type": 16001,
        "name": "桃山小学校",
        "address": "熱海市桃山町6-5",
        "lat": 35.106322,
        "lng": 139.074206
    },
    {
        "code": "B122210000282",
        "type": 16001,
        "name": "泉小学校",
        "address": "熱海市泉280",
        "lat": 35.136041,
        "lng": 139.080776
    },
    {
        "code": "C122210000155",
        "type": 16002,
        "name": "初島中学校",
        "address": "熱海市初島219",
        "lat": 35.042108,
        "lng": 139.170764
    },
    {
        "code": "C122210000164",
        "type": 16002,
        "name": "多賀中学校",
        "address": "熱海市下多賀1549-1",
        "lat": 35.046524,
        "lng": 139.064624
    },
    {
        "code": "C122210000173",
        "type": 16002,
        "name": "泉中学校",
        "address": "熱海市泉280",
        "lat": 35.136041,
        "lng": 139.080789
    },
    {
        "code": "C122210000182",
        "type": 16002,
        "name": "熱海中学校",
        "address": "熱海市桃山町7-7",
        "lat": 35.106572,
        "lng": 139.07529
    },
    {
        "code": "D122210000055",
        "type": 16004,
        "name": "熱海高等学校",
        "address": "熱海市下多賀字向山1484-22",
        "lat": 35.053634,
        "lng": 139.065018
    },
    {
        "code": "H122310000045",
        "type": 16016,
        "name": "国際観光専門学校熱海校",
        "address": "熱海市中央町13-4",
        "lat": 35.094138,
        "lng": 139.07318
    },
    {
        "code": "H122310000054",
        "type": 16016,
        "name": "国際医療管理専門学校熱海校",
        "address": "熱海市中央町13-4",
        "lat": 35.094048,
        "lng": 139.073262
    },
    {
        "code": "H122310000063",
        "type": 16016,
        "name": "東海医療学園専門学校",
        "address": "熱海市桃山町20-7",
        "lat": 35.106131,
        "lng": 139.079531
    },
    {
        "code": "H122310000072",
        "type": 16016,
        "name": "国際ペットビジネス専門学校熱海校",
        "address": "熱海市田原本町9-1",
        "lat": 35.103359,
        "lng": 139.079044
    },
    {
        "code": "H222310000035",
        "type": 16015,
        "name": "熱海共進珠算学校",
        "address": "熱海市桃山町17-11",
        "lat": 35.105074,
        "lng": 139.078331
    }
]