[
    {
        "code": "A123210000309",
        "type": 16011,
        "name": "大浜幼稚園",
        "address": "碧南市浜田町1-119",
        "lat": 34.866858,
        "lng": 136.979763
    },
    {
        "code": "A123210000318",
        "type": 16011,
        "name": "新川幼稚園",
        "address": "碧南市新川町2-123",
        "lat": 34.899394,
        "lng": 136.990816
    },
    {
        "code": "A123210000327",
        "type": 16011,
        "name": "棚尾幼稚園",
        "address": "碧南市春日町2-10",
        "lat": 34.878288,
        "lng": 136.992689
    },
    {
        "code": "A123210000336",
        "type": 16011,
        "name": "西端幼稚園",
        "address": "碧南市上町2-77",
        "lat": 34.915753,
        "lng": 137.012966
    },
    {
        "code": "A123210000345",
        "type": 16011,
        "name": "中央幼稚園",
        "address": "碧南市幸町3-40-1",
        "lat": 34.88789,
        "lng": 137.000796
    },
    {
        "code": "A223310001163",
        "type": 16013,
        "name": "へきなんこども園",
        "address": "碧南市松本町73",
        "lat": 34.884201,
        "lng": 136.995319
    },
    {
        "code": "A223310001172",
        "type": 16013,
        "name": "第２へきなんこども園",
        "address": "碧南市縄手町5-61",
        "lat": 34.88901,
        "lng": 137.025333
    },
    {
        "code": "B123210005053",
        "type": 16001,
        "name": "新川小学校",
        "address": "碧南市新川町2-1",
        "lat": 34.898374,
        "lng": 136.989794
    },
    {
        "code": "B123210005062",
        "type": 16001,
        "name": "大浜小学校",
        "address": "碧南市浜田町1-1",
        "lat": 34.866988,
        "lng": 136.980157
    },
    {
        "code": "B123210005071",
        "type": 16001,
        "name": "棚尾小学校",
        "address": "碧南市春日町1-5",
        "lat": 34.876793,
        "lng": 136.991184
    },
    {
        "code": "B123210005080",
        "type": 16001,
        "name": "日進小学校",
        "address": "碧南市日進町4-1",
        "lat": 34.876766,
        "lng": 137.000266
    },
    {
        "code": "B123210005099",
        "type": 16001,
        "name": "鷲塚小学校",
        "address": "碧南市旭町2-30",
        "lat": 34.888543,
        "lng": 137.016736
    },
    {
        "code": "B123210005106",
        "type": 16001,
        "name": "西端小学校",
        "address": "碧南市上町3-1",
        "lat": 34.915956,
        "lng": 137.01143
    },
    {
        "code": "B123210005115",
        "type": 16001,
        "name": "中央小学校",
        "address": "碧南市向陽町3-19",
        "lat": 34.887959,
        "lng": 136.995655
    },
    {
        "code": "C123210002161",
        "type": 16002,
        "name": "新川中学校",
        "address": "碧南市新川町1-1",
        "lat": 34.900402,
        "lng": 136.990322
    },
    {
        "code": "C123210002170",
        "type": 16002,
        "name": "南中学校",
        "address": "碧南市春日町1-1",
        "lat": 34.877682,
        "lng": 136.990406
    },
    {
        "code": "C123210002189",
        "type": 16002,
        "name": "東中学校",
        "address": "碧南市天神町3-88",
        "lat": 34.888182,
        "lng": 137.007821
    },
    {
        "code": "C123210002198",
        "type": 16002,
        "name": "西端中学校",
        "address": "碧南市神田3-10",
        "lat": 34.917761,
        "lng": 137.014263
    },
    {
        "code": "C123210002205",
        "type": 16002,
        "name": "中央中学校",
        "address": "碧南市植出町5-2",
        "lat": 34.891931,
        "lng": 136.996933
    },
    {
        "code": "D123210001044",
        "type": 16004,
        "name": "碧南高等学校",
        "address": "碧南市向陽町4-12",
        "lat": 34.886293,
        "lng": 136.994461
    },
    {
        "code": "D123210001115",
        "type": 16004,
        "name": "碧南工科高等学校",
        "address": "碧南市丸山町3-10",
        "lat": 34.910151,
        "lng": 136.997376
    },
    {
        "code": "H223310000604",
        "type": 16015,
        "name": "伯人学校イーエーエス碧南",
        "address": "碧南市田尻町4-53",
        "lat": 34.910518,
        "lng": 136.988685
    }
]