[
    {
        "code": "A128210000359",
        "type": 16011,
        "name": "水上幼稚園",
        "address": "姫路市保城5-4",
        "lat": 34.854031,
        "lng": 134.713837
    },
    {
        "code": "A128210000368",
        "type": 16011,
        "name": "城西幼稚園",
        "address": "姫路市新在家3-5-1",
        "lat": 34.845134,
        "lng": 134.683371
    },
    {
        "code": "A128210000377",
        "type": 16011,
        "name": "高岡幼稚園",
        "address": "姫路市西今宿4-4-20",
        "lat": 34.84439,
        "lng": 134.664073
    },
    {
        "code": "A128210000386",
        "type": 16011,
        "name": "曽左幼稚園",
        "address": "姫路市書写台1-62-1",
        "lat": 34.874097,
        "lng": 134.649393
    },
    {
        "code": "A128210000395",
        "type": 16011,
        "name": "城東幼稚園",
        "address": "姫路市城東町野田1-2",
        "lat": 34.834547,
        "lng": 134.708588
    },
    {
        "code": "A128210000402",
        "type": 16011,
        "name": "城陽幼稚園",
        "address": "姫路市北条1064",
        "lat": 34.821068,
        "lng": 134.698876
    },
    {
        "code": "A128210000411",
        "type": 16011,
        "name": "手柄幼稚園",
        "address": "姫路市延末148-2",
        "lat": 34.821249,
        "lng": 134.677462
    },
    {
        "code": "A128210000420",
        "type": 16011,
        "name": "荒川幼稚園",
        "address": "姫路市町坪127",
        "lat": 34.821117,
        "lng": 134.65856
    },
    {
        "code": "A128210000439",
        "type": 16011,
        "name": "糸引幼稚園",
        "address": "姫路市東山91-18",
        "lat": 34.794391,
        "lng": 134.716194
    },
    {
        "code": "A128210000448",
        "type": 16011,
        "name": "白浜幼稚園",
        "address": "姫路市白浜町甲842-2",
        "lat": 34.783655,
        "lng": 134.703693
    },
    {
        "code": "A128210000457",
        "type": 16011,
        "name": "高浜幼稚園",
        "address": "姫路市飾磨区阿成鹿古307",
        "lat": 34.801128,
        "lng": 134.686961
    },
    {
        "code": "A128210000466",
        "type": 16011,
        "name": "飾磨幼稚園",
        "address": "姫路市飾磨区恵美酒22",
        "lat": 34.797747,
        "lng": 134.671998
    },
    {
        "code": "A128210000475",
        "type": 16011,
        "name": "英賀保幼稚園",
        "address": "姫路市飾磨区英賀清水町2-73",
        "lat": 34.806165,
        "lng": 134.644376
    },
    {
        "code": "A128210000484",
        "type": 16011,
        "name": "八幡幼稚園",
        "address": "姫路市広畑区城山町1400-1",
        "lat": 34.825719,
        "lng": 134.637021
    },
    {
        "code": "A128210000493",
        "type": 16011,
        "name": "広畑第二幼稚園",
        "address": "姫路市広畑区高浜町3-35",
        "lat": 34.80128,
        "lng": 134.620467
    },
    {
        "code": "A128210000509",
        "type": 16011,
        "name": "大津幼稚園",
        "address": "姫路市大津区天満1606",
        "lat": 34.797608,
        "lng": 134.607172
    },
    {
        "code": "A128210000518",
        "type": 16011,
        "name": "網干幼稚園",
        "address": "姫路市網干区興浜16",
        "lat": 34.780888,
        "lng": 134.586077
    },
    {
        "code": "A128210000527",
        "type": 16011,
        "name": "勝原幼稚園",
        "address": "姫路市勝原区丁715-1",
        "lat": 34.814695,
        "lng": 134.596728
    },
    {
        "code": "A128210000536",
        "type": 16011,
        "name": "旭陽幼稚園",
        "address": "姫路市網干区坂上430-3",
        "lat": 34.801594,
        "lng": 134.586704
    },
    {
        "code": "A128210000545",
        "type": 16011,
        "name": "花田幼稚園",
        "address": "姫路市花田町加納原田956",
        "lat": 34.835011,
        "lng": 134.726111
    },
    {
        "code": "A128210000554",
        "type": 16011,
        "name": "御国野幼稚園",
        "address": "姫路市御国野町御着1049-3",
        "lat": 34.819942,
        "lng": 134.741666
    },
    {
        "code": "A128210000563",
        "type": 16011,
        "name": "四郷幼稚園",
        "address": "姫路市四郷町坂元251",
        "lat": 34.810994,
        "lng": 134.722223
    },
    {
        "code": "A128210000572",
        "type": 16011,
        "name": "別所幼稚園",
        "address": "姫路市別所町別所1721",
        "lat": 34.808193,
        "lng": 134.756286
    },
    {
        "code": "A128210000581",
        "type": 16011,
        "name": "谷外幼稚園",
        "address": "姫路市飾東町豊国1164-91",
        "lat": 34.844377,
        "lng": 134.740962
    },
    {
        "code": "A128210000590",
        "type": 16011,
        "name": "豊富幼稚園",
        "address": "姫路市豊富町御蔭1113-3",
        "lat": 34.882355,
        "lng": 134.747053
    },
    {
        "code": "A128210000607",
        "type": 16011,
        "name": "大塩幼稚園",
        "address": "姫路市大塩町汐咲2-20-2",
        "lat": 34.779345,
        "lng": 134.755476
    },
    {
        "code": "A128210000616",
        "type": 16011,
        "name": "広峰幼稚園",
        "address": "姫路市北平野2-9-20",
        "lat": 34.860202,
        "lng": 134.694019
    },
    {
        "code": "A128210000625",
        "type": 16011,
        "name": "津田幼稚園",
        "address": "姫路市飾磨区加茂347",
        "lat": 34.80303,
        "lng": 134.659138
    },
    {
        "code": "A128210000634",
        "type": 16011,
        "name": "安室東幼稚園",
        "address": "姫路市辻井8-18-1",
        "lat": 34.854311,
        "lng": 134.672597
    },
    {
        "code": "A128210000643",
        "type": 16011,
        "name": "城乾幼稚園",
        "address": "姫路市南八代町6-53",
        "lat": 34.843993,
        "lng": 134.687565
    },
    {
        "code": "A128210000652",
        "type": 16011,
        "name": "青山幼稚園",
        "address": "姫路市青山北3-42-2",
        "lat": 34.851741,
        "lng": 134.632281
    },
    {
        "code": "A128210002259",
        "type": 16011,
        "name": "坊勢幼稚園",
        "address": "姫路市家島町坊勢303-3",
        "lat": 34.653034,
        "lng": 134.515488
    },
    {
        "code": "A128210002268",
        "type": 16011,
        "name": "家島幼稚園",
        "address": "姫路市家島町真浦2152",
        "lat": 34.674396,
        "lng": 134.529552
    },
    {
        "code": "A128210002277",
        "type": 16011,
        "name": "置塩幼稚園",
        "address": "姫路市夢前町宮置245-2",
        "lat": 34.911159,
        "lng": 134.67427
    },
    {
        "code": "A128210002286",
        "type": 16011,
        "name": "菅生幼稚園",
        "address": "姫路市夢前町菅生澗829-1",
        "lat": 34.916112,
        "lng": 134.641376
    },
    {
        "code": "A128310000767",
        "type": 16011,
        "name": "日ノ本幼稚園",
        "address": "姫路市南新在家5-16",
        "lat": 34.844579,
        "lng": 134.684976
    },
    {
        "code": "A128310000776",
        "type": 16011,
        "name": "フタバ幼稚園",
        "address": "姫路市飾磨区恵美酒55",
        "lat": 34.798909,
        "lng": 134.673201
    },
    {
        "code": "A128310000785",
        "type": 16011,
        "name": "マリア幼稚園",
        "address": "姫路市網干区浜田816-6",
        "lat": 34.778983,
        "lng": 134.577587
    },
    {
        "code": "A128310000794",
        "type": 16011,
        "name": "しげる幼稚園",
        "address": "姫路市町ﾉ坪125",
        "lat": 34.82117,
        "lng": 134.659571
    },
    {
        "code": "A128310000801",
        "type": 16011,
        "name": "エンゼル学園幼稚園",
        "address": "姫路市梅ヶ谷町10-1",
        "lat": 34.85763,
        "lng": 134.690075
    },
    {
        "code": "A128310000810",
        "type": 16011,
        "name": "真愛幼稚園",
        "address": "姫路市書写828",
        "lat": 34.87235,
        "lng": 134.661497
    },
    {
        "code": "A128310001935",
        "type": 16011,
        "name": "真教寺宝国幼稚園",
        "address": "姫路市飾磨区今在家北1-1",
        "lat": 34.809052,
        "lng": 134.656636
    },
    {
        "code": "A228210000287",
        "type": 16013,
        "name": "太市こども園",
        "address": "姫路市西脇500",
        "lat": 34.862343,
        "lng": 134.603267
    },
    {
        "code": "A228210000296",
        "type": 16013,
        "name": "山田こども園",
        "address": "姫路市山田町北山田109-3",
        "lat": 34.912014,
        "lng": 134.774144
    },
    {
        "code": "A228210000303",
        "type": 16013,
        "name": "船津こども園",
        "address": "姫路市船津町1160-3",
        "lat": 34.920671,
        "lng": 134.758615
    },
    {
        "code": "A228210000312",
        "type": 16013,
        "name": "林田こども園",
        "address": "姫路市林田町六九谷510-1",
        "lat": 34.914725,
        "lng": 134.58407
    },
    {
        "code": "A228210000321",
        "type": 16013,
        "name": "的形こども園",
        "address": "姫路市的形町的形1540-1",
        "lat": 34.775409,
        "lng": 134.73917
    },
    {
        "code": "A228210000330",
        "type": 16013,
        "name": "香呂こども園",
        "address": "姫路市香寺町香呂239-1",
        "lat": 34.9126,
        "lng": 134.735238
    },
    {
        "code": "A228210000349",
        "type": 16013,
        "name": "砥堀こども園",
        "address": "姫路市砥堀1258-2",
        "lat": 34.874315,
        "lng": 134.731099
    },
    {
        "code": "A228210000358",
        "type": 16013,
        "name": "前之庄こども園",
        "address": "姫路市夢前町前之庄2197-5",
        "lat": 34.975385,
        "lng": 134.682891
    },
    {
        "code": "A228210000367",
        "type": 16013,
        "name": "安富こども園",
        "address": "姫路市安富町安志1193-1",
        "lat": 34.985975,
        "lng": 134.596624
    },
    {
        "code": "A228210000376",
        "type": 16013,
        "name": "中寺こども園",
        "address": "姫路市香寺町中寺224-2",
        "lat": 34.931619,
        "lng": 134.728819
    },
    {
        "code": "A228310003077",
        "type": 16013,
        "name": "五字ヶ丘幼稚園",
        "address": "姫路市西今宿3-18-30",
        "lat": 34.843654,
        "lng": 134.662124
    },
    {
        "code": "A228310003086",
        "type": 16013,
        "name": "船場御坊幼稚園",
        "address": "姫路市地内町1",
        "lat": 34.833792,
        "lng": 134.682231
    },
    {
        "code": "A228310003095",
        "type": 16013,
        "name": "野里こども園",
        "address": "姫路市威徳寺町33",
        "lat": 34.848587,
        "lng": 134.703192
    },
    {
        "code": "A228310003102",
        "type": 16013,
        "name": "幼保連携型認定こども園ベイカ",
        "address": "姫路市五軒邸3-62-2",
        "lat": 34.836074,
        "lng": 134.702808
    },
    {
        "code": "A228310003111",
        "type": 16013,
        "name": "姫路前山保育園",
        "address": "姫路市御立中5-5-7",
        "lat": 34.867676,
        "lng": 134.667472
    },
    {
        "code": "A228310003120",
        "type": 16013,
        "name": "萩学園",
        "address": "姫路市豊富町豊富1528",
        "lat": 34.893582,
        "lng": 134.744286
    },
    {
        "code": "A228310003139",
        "type": 16013,
        "name": "保城さくらんぼこども園",
        "address": "姫路市保城402-2",
        "lat": 34.858028,
        "lng": 134.717639
    },
    {
        "code": "A228310003148",
        "type": 16013,
        "name": "保城こども園",
        "address": "姫路市保城694-3",
        "lat": 34.857233,
        "lng": 134.719473
    },
    {
        "code": "A228310003157",
        "type": 16013,
        "name": "豊冨台保育園",
        "address": "姫路市豊富町御蔭3278-57",
        "lat": 34.871312,
        "lng": 134.738917
    },
    {
        "code": "A228310003166",
        "type": 16013,
        "name": "チコハウス山びここども園",
        "address": "姫路市広畑区蒲田383-4",
        "lat": 34.836121,
        "lng": 134.647541
    },
    {
        "code": "A228310003175",
        "type": 16013,
        "name": "チコハウス山びここども園分園",
        "address": "姫路市広畑区東新町3-146-10",
        "lat": 34.7992,
        "lng": 134.639269
    },
    {
        "code": "A228310003184",
        "type": 16013,
        "name": "聖ミカエル広畑幼稚園",
        "address": "姫路市広畑区小松町4-36",
        "lat": 34.802849,
        "lng": 134.617562
    },
    {
        "code": "A228310003193",
        "type": 16013,
        "name": "専徳寺保育園",
        "address": "姫路市大津区勘兵衛町2-29-1",
        "lat": 34.790554,
        "lng": 134.613873
    },
    {
        "code": "A228310003200",
        "type": 16013,
        "name": "専徳寺保育園分園",
        "address": "姫路市勝原区熊見96-14",
        "lat": 34.809604,
        "lng": 134.612521
    },
    {
        "code": "A228310003219",
        "type": 16013,
        "name": "徳栄寺こども園",
        "address": "姫路市余部区下余部464-3",
        "lat": 34.796192,
        "lng": 134.579896
    },
    {
        "code": "A228310003228",
        "type": 16013,
        "name": "瑠璃こども園",
        "address": "姫路市網干区大江島寺前町120-2",
        "lat": 34.791562,
        "lng": 134.596095
    },
    {
        "code": "A228310003237",
        "type": 16013,
        "name": "勝原保育園",
        "address": "姫路市勝原区宮田143-3",
        "lat": 34.809657,
        "lng": 134.600339
    },
    {
        "code": "A228310003246",
        "type": 16013,
        "name": "勝原保育園分園",
        "address": "姫路市山戸113-6",
        "lat": 34.808118,
        "lng": 134.603144
    },
    {
        "code": "A228310003255",
        "type": 16013,
        "name": "みどりこども園",
        "address": "姫路市飾東町八重畑1010",
        "lat": 34.856968,
        "lng": 134.772996
    },
    {
        "code": "A228310003264",
        "type": 16013,
        "name": "みどりこども園分園",
        "address": "姫路市飾東町山崎49-3",
        "lat": 34.856273,
        "lng": 134.770171
    },
    {
        "code": "A228310003273",
        "type": 16013,
        "name": "書写認定こども園",
        "address": "姫路市書写2481",
        "lat": 34.872381,
        "lng": 134.65467
    },
    {
        "code": "A228310003282",
        "type": 16013,
        "name": "姫路ひまわり保育園",
        "address": "姫路市北夢前台1-59",
        "lat": 34.86629,
        "lng": 134.662983
    },
    {
        "code": "A228310003291",
        "type": 16013,
        "name": "姫路ひまわり保育園分園",
        "address": "姫路市書写634-50",
        "lat": 34.866847,
        "lng": 134.660317
    },
    {
        "code": "A228310003308",
        "type": 16013,
        "name": "みねあい保育園",
        "address": "姫路市六角278-2",
        "lat": 34.883727,
        "lng": 134.636836
    },
    {
        "code": "A228310003317",
        "type": 16013,
        "name": "荒川ひまわり保育園手柄分園",
        "address": "姫路市手柄95",
        "lat": 34.817079,
        "lng": 134.676767
    },
    {
        "code": "A228310003326",
        "type": 16013,
        "name": "サンこども園",
        "address": "姫路市白鳥台2-28-1",
        "lat": 34.884968,
        "lng": 134.620734
    },
    {
        "code": "A228310003335",
        "type": 16013,
        "name": "津田このみ学園",
        "address": "姫路市飾磨区今在家6-133",
        "lat": 34.804986,
        "lng": 134.658233
    },
    {
        "code": "A228310003344",
        "type": 16013,
        "name": "津田このみ学園三宅分園",
        "address": "姫路市飾磨区三宅1-52",
        "lat": 34.811816,
        "lng": 134.68123
    },
    {
        "code": "A228310003353",
        "type": 16013,
        "name": "こじかこども園",
        "address": "姫路市飾磨区中野田4-123",
        "lat": 34.803547,
        "lng": 134.683727
    },
    {
        "code": "A228310003362",
        "type": 16013,
        "name": "八木保育園",
        "address": "姫路市木場前中町46",
        "lat": 34.779664,
        "lng": 134.720191
    },
    {
        "code": "A228310003371",
        "type": 16013,
        "name": "八木保育園分園",
        "address": "姫路市白浜町甲337-8",
        "lat": 34.786954,
        "lng": 134.708207
    },
    {
        "code": "A228310003380",
        "type": 16013,
        "name": "三恵城山こども園",
        "address": "姫路市夢前町宮置79-2",
        "lat": 34.90974,
        "lng": 134.671654
    },
    {
        "code": "A228310003399",
        "type": 16013,
        "name": "すごう保育園",
        "address": "姫路市夢前町菅生澗705-1",
        "lat": 34.914795,
        "lng": 134.638324
    },
    {
        "code": "A228310003406",
        "type": 16013,
        "name": "姫路日ノ本短期大学付属幼稚園",
        "address": "姫路市香寺町相坂467",
        "lat": 34.917205,
        "lng": 134.72612
    },
    {
        "code": "A228310003415",
        "type": 16013,
        "name": "クローバーこども園",
        "address": "姫路市車崎1-9-10",
        "lat": 34.838691,
        "lng": 134.676308
    },
    {
        "code": "A228310003424",
        "type": 16013,
        "name": "広峰保育園",
        "address": "姫路市北平野奥垣内7-3",
        "lat": 34.868182,
        "lng": 134.697772
    },
    {
        "code": "A228310003433",
        "type": 16013,
        "name": "姫路東こども園",
        "address": "姫路市東山49-1",
        "lat": 34.794007,
        "lng": 134.718571
    },
    {
        "code": "A228310003442",
        "type": 16013,
        "name": "妻鹿みどりこども園",
        "address": "姫路市飾磨区妻鹿312-1",
        "lat": 34.793168,
        "lng": 134.697004
    },
    {
        "code": "A228310003451",
        "type": 16013,
        "name": "別所まるやまこども園",
        "address": "姫路市別所町佐土2-77",
        "lat": 34.813306,
        "lng": 134.747404
    },
    {
        "code": "A228310003460",
        "type": 16013,
        "name": "青葉台こども園",
        "address": "姫路市香寺町須加院351",
        "lat": 34.901359,
        "lng": 134.71978
    },
    {
        "code": "A228310003479",
        "type": 16013,
        "name": "安室保育園",
        "address": "姫路市田寺3-3-15",
        "lat": 34.854269,
        "lng": 134.667511
    },
    {
        "code": "A228310003488",
        "type": 16013,
        "name": "ほうこく保育園",
        "address": "姫路市飾磨区今在家941",
        "lat": 34.80132,
        "lng": 134.651935
    },
    {
        "code": "A228310003497",
        "type": 16013,
        "name": "専徳寺ひろはた保育園",
        "address": "姫路市広畑区小松町3-71",
        "lat": 34.803158,
        "lng": 134.621867
    },
    {
        "code": "A228310003503",
        "type": 16013,
        "name": "やながせ保育園",
        "address": "姫路市勝原区下太田571",
        "lat": 34.821081,
        "lng": 134.59538
    },
    {
        "code": "A228310003512",
        "type": 16013,
        "name": "みどりヶ丘幼児園",
        "address": "姫路市八代緑ヶ丘町6-26",
        "lat": 34.853391,
        "lng": 134.690883
    },
    {
        "code": "A228310003521",
        "type": 16013,
        "name": "播磨灘こども園",
        "address": "姫路市広畑区才850-1",
        "lat": 34.80701,
        "lng": 134.625228
    },
    {
        "code": "A228310003530",
        "type": 16013,
        "name": "姫路保育園",
        "address": "姫路市野里堀留町10-18",
        "lat": 34.844196,
        "lng": 134.702383
    },
    {
        "code": "A228310003549",
        "type": 16013,
        "name": "姫路保育園イーグレ分園",
        "address": "姫路市本町68-290ｲｰｸﾞﾚひめじ1F",
        "lat": 34.833704,
        "lng": 134.694103
    },
    {
        "code": "A228310003558",
        "type": 16013,
        "name": "瑠璃よこはまこども園",
        "address": "姫路市網干区余子浜2001",
        "lat": 34.788729,
        "lng": 134.582745
    },
    {
        "code": "A228310003567",
        "type": 16013,
        "name": "荒川ひまわり保育園",
        "address": "姫路市玉手3-510",
        "lat": 34.814315,
        "lng": 134.664314
    },
    {
        "code": "A228310003576",
        "type": 16013,
        "name": "専徳寺ひろはた保育園とまみ分園",
        "address": "姫路市苫編401-1",
        "lat": 34.803049,
        "lng": 134.621935
    },
    {
        "code": "A228310004147",
        "type": 16013,
        "name": "やながせ保育園大津みやび野分園",
        "address": "姫路市大津区大津町1-31-111",
        "lat": 34.805361,
        "lng": 134.61126
    },
    {
        "code": "A228310004254",
        "type": 16013,
        "name": "みどりケ丘幼児園かまえ分園",
        "address": "姫路市飾磨区構3-62",
        "lat": 34.853407,
        "lng": 134.690945
    },
    {
        "code": "B128210005058",
        "type": 16001,
        "name": "砥堀小学校",
        "address": "姫路市砥堀1240-3",
        "lat": 34.875417,
        "lng": 134.730729
    },
    {
        "code": "B128210005067",
        "type": 16001,
        "name": "水上小学校",
        "address": "姫路市西中島382",
        "lat": 34.854354,
        "lng": 134.713666
    },
    {
        "code": "B128210005076",
        "type": 16001,
        "name": "城北小学校",
        "address": "姫路市伊伝居600-2",
        "lat": 34.849642,
        "lng": 134.697344
    },
    {
        "code": "B128210005085",
        "type": 16001,
        "name": "野里小学校",
        "address": "姫路市坊主町3-1",
        "lat": 34.843393,
        "lng": 134.697872
    },
    {
        "code": "B128210005094",
        "type": 16001,
        "name": "城西小学校",
        "address": "姫路市新在家2-4-1",
        "lat": 34.844809,
        "lng": 134.681818
    },
    {
        "code": "B128210005101",
        "type": 16001,
        "name": "安室小学校",
        "address": "姫路市田寺6-11-12",
        "lat": 34.859252,
        "lng": 134.667625
    },
    {
        "code": "B128210005110",
        "type": 16001,
        "name": "高岡小学校",
        "address": "姫路市西今宿4-8-1",
        "lat": 34.845948,
        "lng": 134.663764
    },
    {
        "code": "B128210005129",
        "type": 16001,
        "name": "曽左小学校",
        "address": "姫路市書写634-51",
        "lat": 34.86814,
        "lng": 134.660959
    },
    {
        "code": "B128210005138",
        "type": 16001,
        "name": "白鳥小学校",
        "address": "姫路市飾西341",
        "lat": 34.863223,
        "lng": 134.642627
    },
    {
        "code": "B128210005147",
        "type": 16001,
        "name": "太市小学校",
        "address": "姫路市西脇507",
        "lat": 34.863167,
        "lng": 134.603186
    },
    {
        "code": "B128210005156",
        "type": 16001,
        "name": "東小学校",
        "address": "姫路市市之郷町2-34",
        "lat": 34.826478,
        "lng": 134.709455
    },
    {
        "code": "B128210005165",
        "type": 16001,
        "name": "城東小学校",
        "address": "姫路市城東町竹之門1",
        "lat": 34.836422,
        "lng": 134.704539
    },
    {
        "code": "B128210005174",
        "type": 16001,
        "name": "船場小学校",
        "address": "姫路市東雲町1-29",
        "lat": 34.832811,
        "lng": 134.683068
    },
    {
        "code": "B128210005183",
        "type": 16001,
        "name": "城陽小学校",
        "address": "姫路市北条923-1",
        "lat": 34.821951,
        "lng": 134.697345
    },
    {
        "code": "B128210005192",
        "type": 16001,
        "name": "手柄小学校",
        "address": "姫路市延末148-2",
        "lat": 34.821506,
        "lng": 134.677875
    },
    {
        "code": "B128210005209",
        "type": 16001,
        "name": "荒川小学校",
        "address": "姫路市井ﾉ口49-1",
        "lat": 34.821951,
        "lng": 134.661599
    },
    {
        "code": "B128210005218",
        "type": 16001,
        "name": "八木小学校",
        "address": "姫路市八家24-2",
        "lat": 34.783442,
        "lng": 134.727924
    },
    {
        "code": "B128210005227",
        "type": 16001,
        "name": "糸引小学校",
        "address": "姫路市東山114-1",
        "lat": 34.794621,
        "lng": 134.717427
    },
    {
        "code": "B128210005236",
        "type": 16001,
        "name": "白浜小学校",
        "address": "姫路市白浜町甲458",
        "lat": 34.785816,
        "lng": 134.704984
    },
    {
        "code": "B128210005245",
        "type": 16001,
        "name": "妻鹿小学校",
        "address": "姫路市飾磨区妻鹿786-3",
        "lat": 34.788621,
        "lng": 134.695207
    },
    {
        "code": "B128210005254",
        "type": 16001,
        "name": "高浜小学校",
        "address": "姫路市飾磨区阿成鹿古250",
        "lat": 34.799542,
        "lng": 134.686082
    },
    {
        "code": "B128210005263",
        "type": 16001,
        "name": "飾磨小学校",
        "address": "姫路市飾磨区恵美酒22",
        "lat": 34.798786,
        "lng": 134.672404
    },
    {
        "code": "B128210005272",
        "type": 16001,
        "name": "英賀保小学校",
        "address": "姫路市飾磨区英賀清水町2-76",
        "lat": 34.806952,
        "lng": 134.644407
    },
    {
        "code": "B128210005281",
        "type": 16001,
        "name": "八幡小学校",
        "address": "姫路市広畑区西蒲田1400-24",
        "lat": 34.824644,
        "lng": 134.636907
    },
    {
        "code": "B128210005290",
        "type": 16001,
        "name": "広畑小学校",
        "address": "姫路市広畑区清水町1-47",
        "lat": 34.804397,
        "lng": 134.632519
    },
    {
        "code": "B128210005307",
        "type": 16001,
        "name": "広畑第二小学校",
        "address": "姫路市広畑区高浜町3-35",
        "lat": 34.80123,
        "lng": 134.621854
    },
    {
        "code": "B128210005316",
        "type": 16001,
        "name": "大津小学校",
        "address": "姫路市大津区天満1001-4",
        "lat": 34.797425,
        "lng": 134.606383
    },
    {
        "code": "B128210005325",
        "type": 16001,
        "name": "網干小学校",
        "address": "姫路市網干区新在家897-1",
        "lat": 34.782008,
        "lng": 134.592684
    },
    {
        "code": "B128210005334",
        "type": 16001,
        "name": "勝原小学校",
        "address": "姫路市勝原区丁735-3",
        "lat": 34.814673,
        "lng": 134.598244
    },
    {
        "code": "B128210005343",
        "type": 16001,
        "name": "旭陽小学校",
        "address": "姫路市網干区坂上425-1",
        "lat": 34.801286,
        "lng": 134.586607
    },
    {
        "code": "B128210005352",
        "type": 16001,
        "name": "余部小学校",
        "address": "姫路市余部区上余部643-1",
        "lat": 34.800536,
        "lng": 134.572746
    },
    {
        "code": "B128210005361",
        "type": 16001,
        "name": "花田小学校",
        "address": "姫路市花田町勅旨264-2",
        "lat": 34.834738,
        "lng": 134.725091
    },
    {
        "code": "B128210005370",
        "type": 16001,
        "name": "御国野小学校",
        "address": "姫路市御国野町御着1049-3",
        "lat": 34.820374,
        "lng": 134.74213
    },
    {
        "code": "B128210005389",
        "type": 16001,
        "name": "別所小学校",
        "address": "姫路市別所町別所673",
        "lat": 34.80937,
        "lng": 134.75545
    },
    {
        "code": "B128210005398",
        "type": 16001,
        "name": "谷外小学校",
        "address": "姫路市飾東町豊国560",
        "lat": 34.844338,
        "lng": 134.741951
    },
    {
        "code": "B128210005405",
        "type": 16001,
        "name": "谷内小学校",
        "address": "姫路市飾東町八重畑130-1",
        "lat": 34.856642,
        "lng": 134.777337
    },
    {
        "code": "B128210005414",
        "type": 16001,
        "name": "船津小学校",
        "address": "姫路市船津町921-2",
        "lat": 34.918719,
        "lng": 134.757698
    },
    {
        "code": "B128210005423",
        "type": 16001,
        "name": "山田小学校",
        "address": "姫路市山田町北山田108",
        "lat": 34.911275,
        "lng": 134.774113
    },
    {
        "code": "B128210005432",
        "type": 16001,
        "name": "的形小学校",
        "address": "姫路市的形町的形1619",
        "lat": 34.775804,
        "lng": 134.740374
    },
    {
        "code": "B128210005441",
        "type": 16001,
        "name": "林田小学校",
        "address": "姫路市林田町六九谷523",
        "lat": 34.913745,
        "lng": 134.583048
    },
    {
        "code": "B128210005450",
        "type": 16001,
        "name": "伊勢小学校",
        "address": "姫路市林田町上伊勢886-1",
        "lat": 34.901858,
        "lng": 134.608546
    },
    {
        "code": "B128210005469",
        "type": 16001,
        "name": "大塩小学校",
        "address": "姫路市大塩町汐咲2-19",
        "lat": 34.778818,
        "lng": 134.754784
    },
    {
        "code": "B128210005478",
        "type": 16001,
        "name": "広峰小学校",
        "address": "姫路市峰南町2-1",
        "lat": 34.857447,
        "lng": 134.6959
    },
    {
        "code": "B128210005487",
        "type": 16001,
        "name": "津田小学校",
        "address": "姫路市飾磨区今在家3-233",
        "lat": 34.803369,
        "lng": 134.6581
    },
    {
        "code": "B128210005496",
        "type": 16001,
        "name": "大津茂小学校",
        "address": "姫路市網干区田井22",
        "lat": 34.802313,
        "lng": 134.599633
    },
    {
        "code": "B128210005502",
        "type": 16001,
        "name": "網干西小学校",
        "address": "姫路市網干区浜田24",
        "lat": 34.781093,
        "lng": 134.578636
    },
    {
        "code": "B128210005511",
        "type": 16001,
        "name": "安室東小学校",
        "address": "姫路市田寺東2-5-1",
        "lat": 34.855363,
        "lng": 134.673152
    },
    {
        "code": "B128210005520",
        "type": 16001,
        "name": "峰相小学校",
        "address": "姫路市打越582-1",
        "lat": 34.884138,
        "lng": 134.635183
    },
    {
        "code": "B128210005539",
        "type": 16001,
        "name": "高岡西小学校",
        "address": "姫路市上手野1-1",
        "lat": 34.848114,
        "lng": 134.655793
    },
    {
        "code": "B128210005548",
        "type": 16001,
        "name": "城乾小学校",
        "address": "姫路市南八代町6-60",
        "lat": 34.843365,
        "lng": 134.686762
    },
    {
        "code": "B128210005557",
        "type": 16001,
        "name": "増位小学校",
        "address": "姫路市白国5-9-1",
        "lat": 34.863474,
        "lng": 134.702927
    },
    {
        "code": "B128210005566",
        "type": 16001,
        "name": "南大津小学校",
        "address": "姫路市大津区真砂町40-2",
        "lat": 34.787787,
        "lng": 134.606439
    },
    {
        "code": "B128210005575",
        "type": 16001,
        "name": "青山小学校",
        "address": "姫路市青山北3-42-1",
        "lat": 34.851891,
        "lng": 134.632962
    },
    {
        "code": "B128210005824",
        "type": 16001,
        "name": "家島小学校",
        "address": "姫路市家島町真浦2141",
        "lat": 34.674424,
        "lng": 134.53
    },
    {
        "code": "B128210005833",
        "type": 16001,
        "name": "坊勢小学校",
        "address": "姫路市家島町坊勢415-1",
        "lat": 34.652724,
        "lng": 134.514622
    },
    {
        "code": "B128210005842",
        "type": 16001,
        "name": "置塩小学校",
        "address": "姫路市夢前町宮置235",
        "lat": 34.911378,
        "lng": 134.673971
    },
    {
        "code": "B128210005851",
        "type": 16001,
        "name": "古知小学校",
        "address": "姫路市夢前町古知之庄401-1",
        "lat": 34.946487,
        "lng": 134.678316
    },
    {
        "code": "B128210005860",
        "type": 16001,
        "name": "前之庄小学校",
        "address": "姫路市夢前町前之庄2838-1",
        "lat": 34.97244,
        "lng": 134.681343
    },
    {
        "code": "B128210005879",
        "type": 16001,
        "name": "上菅小学校",
        "address": "姫路市夢前町護持381-2",
        "lat": 34.9428,
        "lng": 134.634161
    },
    {
        "code": "B128210005888",
        "type": 16001,
        "name": "菅生小学校",
        "address": "姫路市夢前町菅生澗802-1",
        "lat": 34.916281,
        "lng": 134.642089
    },
    {
        "code": "B128210005897",
        "type": 16001,
        "name": "莇野小学校",
        "address": "姫路市夢前町莇野299-2",
        "lat": 34.976171,
        "lng": 134.632763
    },
    {
        "code": "B128210005995",
        "type": 16001,
        "name": "香呂小学校",
        "address": "姫路市香寺町香呂626",
        "lat": 34.911596,
        "lng": 134.73085
    },
    {
        "code": "B128210006002",
        "type": 16001,
        "name": "中寺小学校",
        "address": "姫路市香寺町中寺231",
        "lat": 34.931515,
        "lng": 134.729483
    },
    {
        "code": "B128210006011",
        "type": 16001,
        "name": "香呂南小学校",
        "address": "姫路市香寺町須加院173",
        "lat": 34.89454,
        "lng": 134.726505
    },
    {
        "code": "B128210006333",
        "type": 16001,
        "name": "安富南小学校",
        "address": "姫路市安富町安志869",
        "lat": 34.985717,
        "lng": 134.590774
    },
    {
        "code": "B128210006342",
        "type": 16001,
        "name": "安富北小学校",
        "address": "姫路市安富町杤原664-2",
        "lat": 35.020914,
        "lng": 134.604249
    },
    {
        "code": "C128210002353",
        "type": 16002,
        "name": "増位中学校",
        "address": "姫路市増位新町2-4-1",
        "lat": 34.863446,
        "lng": 134.702927
    },
    {
        "code": "C128210002362",
        "type": 16002,
        "name": "広嶺中学校",
        "address": "姫路市峰南町2-43",
        "lat": 34.859641,
        "lng": 134.695761
    },
    {
        "code": "C128210002371",
        "type": 16002,
        "name": "高丘中学校",
        "address": "姫路市山吹1-4-13",
        "lat": 34.850475,
        "lng": 134.664375
    },
    {
        "code": "C128210002380",
        "type": 16002,
        "name": "大白書中学校",
        "address": "姫路市飾西652",
        "lat": 34.858835,
        "lng": 134.645849
    },
    {
        "code": "C128210002399",
        "type": 16002,
        "name": "東光中学校",
        "address": "姫路市国府寺町80",
        "lat": 34.834589,
        "lng": 134.702705
    },
    {
        "code": "C128210002406",
        "type": 16002,
        "name": "琴陵中学校",
        "address": "姫路市山畑新田525",
        "lat": 34.83806,
        "lng": 134.677958
    },
    {
        "code": "C128210002415",
        "type": 16002,
        "name": "山陽中学校",
        "address": "姫路市延末103-1",
        "lat": 34.822867,
        "lng": 134.678291
    },
    {
        "code": "C128210002424",
        "type": 16002,
        "name": "灘中学校",
        "address": "姫路市白浜町神田1-33",
        "lat": 34.791371,
        "lng": 134.706039
    },
    {
        "code": "C128210002433",
        "type": 16002,
        "name": "飾磨東中学校",
        "address": "姫路市飾磨区三和町26",
        "lat": 34.799092,
        "lng": 134.683041
    },
    {
        "code": "C128210002442",
        "type": 16002,
        "name": "飾磨中部中学校",
        "address": "姫路市飾磨区細江206",
        "lat": 34.803092,
        "lng": 134.670515
    },
    {
        "code": "C128210002451",
        "type": 16002,
        "name": "飾磨西中学校",
        "address": "姫路市飾磨区構2-93",
        "lat": 34.809146,
        "lng": 134.661321
    },
    {
        "code": "C128210002460",
        "type": 16002,
        "name": "広畑中学校",
        "address": "姫路市広畑区小松町3-83",
        "lat": 34.802091,
        "lng": 134.621409
    },
    {
        "code": "C128210002479",
        "type": 16002,
        "name": "網干中学校",
        "address": "姫路市網干区新在家1320-4",
        "lat": 34.785759,
        "lng": 134.591357
    },
    {
        "code": "C128210002488",
        "type": 16002,
        "name": "朝日中学校",
        "address": "姫路市網干区坂出1-1",
        "lat": 34.803758,
        "lng": 134.590384
    },
    {
        "code": "C128210002497",
        "type": 16002,
        "name": "城山中学校",
        "address": "姫路市飾東町豊国1163-5",
        "lat": 34.847754,
        "lng": 134.746617
    },
    {
        "code": "C128210002503",
        "type": 16002,
        "name": "神南中学校",
        "address": "姫路市船津町3937",
        "lat": 34.908553,
        "lng": 134.757476
    },
    {
        "code": "C128210002512",
        "type": 16002,
        "name": "花田中学校",
        "address": "姫路市花田町小川1246-1",
        "lat": 34.847337,
        "lng": 134.723147
    },
    {
        "code": "C128210002521",
        "type": 16002,
        "name": "林田中学校",
        "address": "姫路市林田町林田33",
        "lat": 34.904802,
        "lng": 134.580187
    },
    {
        "code": "C128210002530",
        "type": 16002,
        "name": "夢前中学校",
        "address": "姫路市広畑区才226-1",
        "lat": 34.815534,
        "lng": 134.629436
    },
    {
        "code": "C128210002549",
        "type": 16002,
        "name": "城乾中学校",
        "address": "姫路市南八代町6-1",
        "lat": 34.842449,
        "lng": 134.686179
    },
    {
        "code": "C128210002558",
        "type": 16002,
        "name": "大的中学校",
        "address": "姫路市大塩町2213-2",
        "lat": 34.776263,
        "lng": 134.752145
    },
    {
        "code": "C128210002567",
        "type": 16002,
        "name": "安室中学校",
        "address": "姫路市田寺東2-6-1",
        "lat": 34.855558,
        "lng": 134.672152
    },
    {
        "code": "C128210002576",
        "type": 16002,
        "name": "書写中学校",
        "address": "姫路市書写台2-34",
        "lat": 34.86875,
        "lng": 134.646877
    },
    {
        "code": "C128210002585",
        "type": 16002,
        "name": "大津中学校",
        "address": "姫路市大津区長松229",
        "lat": 34.799175,
        "lng": 134.602689
    },
    {
        "code": "C128210002692",
        "type": 16002,
        "name": "家島中学校",
        "address": "姫路市家島町宮1877-2",
        "lat": 34.668435,
        "lng": 134.530586
    },
    {
        "code": "C128210002709",
        "type": 16002,
        "name": "坊勢中学校",
        "address": "姫路市家島町坊勢430-1",
        "lat": 34.651205,
        "lng": 134.514134
    },
    {
        "code": "C128210002718",
        "type": 16002,
        "name": "置塩中学校",
        "address": "姫路市夢前町又坂50",
        "lat": 34.927348,
        "lng": 134.673629
    },
    {
        "code": "C128210002727",
        "type": 16002,
        "name": "鹿谷中学校",
        "address": "姫路市夢前町前之庄2860",
        "lat": 34.972223,
        "lng": 134.682319
    },
    {
        "code": "C128210002736",
        "type": 16002,
        "name": "菅野中学校",
        "address": "姫路市夢前町護持29-1",
        "lat": 34.941279,
        "lng": 134.639111
    },
    {
        "code": "C128210002781",
        "type": 16002,
        "name": "香寺中学校",
        "address": "姫路市香寺町岩部293",
        "lat": 34.9188,
        "lng": 134.736513
    },
    {
        "code": "C128210002932",
        "type": 16002,
        "name": "安富中学校",
        "address": "姫路市安富町安志320-1",
        "lat": 34.990317,
        "lng": 134.593655
    },
    {
        "code": "C128210003370",
        "type": 16002,
        "name": "東中学校",
        "address": "姫路市別所町別所30-2",
        "lat": 34.815134,
        "lng": 134.752456
    },
    {
        "code": "C128310000219",
        "type": 16002,
        "name": "姫路女学院中学校",
        "address": "姫路市豊沢町83",
        "lat": 34.823772,
        "lng": 134.689651
    },
    {
        "code": "C128310000228",
        "type": 16002,
        "name": "日ノ本学園中学校",
        "address": "姫路市香寺町香呂890",
        "lat": 34.918409,
        "lng": 134.728213
    },
    {
        "code": "C128310000237",
        "type": 16002,
        "name": "賢明女子学院中学校",
        "address": "姫路市本町68",
        "lat": 34.835691,
        "lng": 134.697902
    },
    {
        "code": "C128310000246",
        "type": 16002,
        "name": "淳心学院中学校",
        "address": "姫路市本町68",
        "lat": 34.837165,
        "lng": 134.697875
    },
    {
        "code": "C128310000255",
        "type": 16002,
        "name": "姫路中学校",
        "address": "姫路市書写木ﾉ下1699",
        "lat": 34.876685,
        "lng": 134.657214
    },
    {
        "code": "C228210000023",
        "type": 16014,
        "name": "白鷺小中学校",
        "address": "姫路市本町68-52",
        "lat": 34.835105,
        "lng": 134.689973
    },
    {
        "code": "C228210000032",
        "type": 16014,
        "name": "四郷学院",
        "address": "姫路市四郷町坂元345-2",
        "lat": 34.811824,
        "lng": 134.720287
    },
    {
        "code": "C228210000041",
        "type": 16014,
        "name": "豊富小中学校",
        "address": "姫路市豊富町御蔭925",
        "lat": 34.882155,
        "lng": 134.748466
    },
    {
        "code": "D128210000086",
        "type": 16004,
        "name": "姫路西高等学校",
        "address": "姫路市北八代2-1-33",
        "lat": 34.849448,
        "lng": 134.695039
    },
    {
        "code": "D128210000095",
        "type": 16004,
        "name": "姫路南高等学校",
        "address": "姫路市大津区天満191-5",
        "lat": 34.803313,
        "lng": 134.610104
    },
    {
        "code": "D128210000102",
        "type": 16004,
        "name": "姫路工業高等学校",
        "address": "姫路市伊伝居600-1",
        "lat": 34.848198,
        "lng": 134.69865
    },
    {
        "code": "D128210000111",
        "type": 16004,
        "name": "飾磨工業高等学校",
        "address": "姫路市飾磨区細江319",
        "lat": 34.801258,
        "lng": 134.668848
    },
    {
        "code": "D128210000120",
        "type": 16004,
        "name": "姫路商業高等学校",
        "address": "姫路市井ﾉ口468",
        "lat": 34.825283,
        "lng": 134.656627
    },
    {
        "code": "D128210000442",
        "type": 16004,
        "name": "姫路東高等学校",
        "address": "姫路市本町68-70",
        "lat": 34.840451,
        "lng": 134.699178
    },
    {
        "code": "D128210000665",
        "type": 16004,
        "name": "姫路別所高等学校",
        "address": "姫路市別所町北宿303-1",
        "lat": 34.809122,
        "lng": 134.767899
    },
    {
        "code": "D128210000674",
        "type": 16004,
        "name": "夢前高等学校",
        "address": "姫路市夢前町前之庄643-1",
        "lat": 34.961491,
        "lng": 134.685943
    },
    {
        "code": "D128210000683",
        "type": 16004,
        "name": "家島高等学校",
        "address": "姫路市家島町宮1759-1",
        "lat": 34.668825,
        "lng": 134.529952
    },
    {
        "code": "D128210000718",
        "type": 16004,
        "name": "香寺高等学校",
        "address": "姫路市香寺町土師547",
        "lat": 34.93221,
        "lng": 134.735244
    },
    {
        "code": "D128210001049",
        "type": 16004,
        "name": "姫路北高等学校",
        "address": "姫路市本町68-70",
        "lat": 34.840421,
        "lng": 134.699178
    },
    {
        "code": "D128210001129",
        "type": 16004,
        "name": "網干高等学校",
        "address": "姫路市網干区新在家259-1",
        "lat": 34.773676,
        "lng": 134.592441
    },
    {
        "code": "D128210001254",
        "type": 16004,
        "name": "姫路飾西高等学校",
        "address": "姫路市飾西字側町148-2",
        "lat": 34.860385,
        "lng": 134.635744
    },
    {
        "code": "D128210001389",
        "type": 16004,
        "name": "姫路市立姫路高等学校",
        "address": "姫路市辻井9-1-10",
        "lat": 34.850447,
        "lng": 134.678152
    },
    {
        "code": "D128210001398",
        "type": 16004,
        "name": "姫路市立琴丘高等学校",
        "address": "姫路市今宿668",
        "lat": 34.837143,
        "lng": 134.660321
    },
    {
        "code": "D128210001405",
        "type": 16004,
        "name": "姫路市立飾磨高等学校",
        "address": "姫路市飾磨区妻鹿672",
        "lat": 34.793426,
        "lng": 134.699151
    },
    {
        "code": "D128310000235",
        "type": 16004,
        "name": "姫路女学院高等学校",
        "address": "姫路市豊沢町83",
        "lat": 34.823562,
        "lng": 134.689429
    },
    {
        "code": "D128310000244",
        "type": 16004,
        "name": "日ノ本学園高等学校",
        "address": "姫路市香寺町香呂890",
        "lat": 34.918285,
        "lng": 134.728196
    },
    {
        "code": "D128310000253",
        "type": 16004,
        "name": "賢明女子学院高等学校",
        "address": "姫路市本町68",
        "lat": 34.835672,
        "lng": 134.6979
    },
    {
        "code": "D128310000262",
        "type": 16004,
        "name": "淳心学院高等学校",
        "address": "姫路市本町68",
        "lat": 34.837144,
        "lng": 134.697873
    },
    {
        "code": "D128310000271",
        "type": 16004,
        "name": "東洋大学附属姫路高等学校",
        "address": "姫路市書写字木ﾉ下1699",
        "lat": 34.87686,
        "lng": 134.657522
    },
    {
        "code": "D128310000486",
        "type": 16004,
        "name": "自由ヶ丘高等学校",
        "address": "姫路市夢前町戸倉566",
        "lat": 34.972135,
        "lng": 134.639501
    },
    {
        "code": "E128210000047",
        "type": 16012,
        "name": "姫路聴覚特別支援学校",
        "address": "姫路市本町68",
        "lat": 34.836671,
        "lng": 134.687846
    },
    {
        "code": "E128210000118",
        "type": 16012,
        "name": "姫路しらさぎ特別支援学校",
        "address": "姫路市苫編688-2",
        "lat": 34.822542,
        "lng": 134.654442
    },
    {
        "code": "E128210000172",
        "type": 16012,
        "name": "姫路特別支援学校",
        "address": "姫路市四郷町東阿保字下戸明476",
        "lat": 34.813285,
        "lng": 134.715232
    },
    {
        "code": "E128210000289",
        "type": 16012,
        "name": "書写養護学校",
        "address": "姫路市書写台3-148-1",
        "lat": 34.866579,
        "lng": 134.646953
    },
    {
        "code": "F128310108918",
        "type": 16007,
        "name": "姫路獨協大学",
        "address": "姫路市上大野7-2-1",
        "lat": 34.872695,
        "lng": 134.689178
    },
    {
        "code": "F128310109007",
        "type": 16007,
        "name": "姫路大学",
        "address": "姫路市大塩町2042-2",
        "lat": 34.772655,
        "lng": 134.759077
    },
    {
        "code": "F228310109177",
        "type": 16006,
        "name": "姫路日ノ本短期大学",
        "address": "姫路市香寺町香呂890-1",
        "lat": 34.918552,
        "lng": 134.728034
    },
    {
        "code": "H128310000021",
        "type": 16016,
        "name": "姫路赤十字看護専門学校",
        "address": "姫路市下手野1-12-2",
        "lat": 34.843417,
        "lng": 134.646441
    },
    {
        "code": "H128310000174",
        "type": 16016,
        "name": "姫路経営医療専門学校",
        "address": "姫路市阿保甲499-4",
        "lat": 34.82282,
        "lng": 134.699784
    },
    {
        "code": "H128310000183",
        "type": 16016,
        "name": "日本調理製菓専門学校",
        "address": "姫路市安田1-2",
        "lat": 34.819865,
        "lng": 134.685935
    },
    {
        "code": "H128310000254",
        "type": 16016,
        "name": "姫路理容美容専門学校",
        "address": "姫路市南駅前町13",
        "lat": 34.824617,
        "lng": 134.693532
    },
    {
        "code": "H128310000334",
        "type": 16016,
        "name": "日本栄養専門学校",
        "address": "姫路市東延末2-165",
        "lat": 34.822362,
        "lng": 134.687096
    },
    {
        "code": "H128310000414",
        "type": 16016,
        "name": "姫路情報システム専門学校",
        "address": "姫路市東延末2-25",
        "lat": 34.82189,
        "lng": 134.68571
    },
    {
        "code": "H128310000469",
        "type": 16016,
        "name": "姫路福祉保育専門学校",
        "address": "姫路市手柄1-22-1",
        "lat": 34.813689,
        "lng": 134.678624
    },
    {
        "code": "H128310000511",
        "type": 16016,
        "name": "日本工科大学校",
        "address": "姫路市兼田383-22",
        "lat": 34.804895,
        "lng": 134.696407
    },
    {
        "code": "H128310000637",
        "type": 16016,
        "name": "姫路市医師会看護専門学校",
        "address": "姫路市御立西5-6-22",
        "lat": 34.862729,
        "lng": 134.661161
    },
    {
        "code": "H128310000664",
        "type": 16016,
        "name": "アルファジャパン美容専門学校",
        "address": "姫路市綿町148",
        "lat": 34.832464,
        "lng": 134.694104
    },
    {
        "code": "H128310000673",
        "type": 16016,
        "name": "姫路歯科衛生専門学校",
        "address": "姫路市阿保甲499-4",
        "lat": 34.822658,
        "lng": 134.699991
    },
    {
        "code": "H128310000708",
        "type": 16016,
        "name": "姫路ハーベスト医療福祉専門学校",
        "address": "姫路市南駅前町91-6",
        "lat": 34.825837,
        "lng": 134.691848
    },
    {
        "code": "H128310000753",
        "type": 16016,
        "name": "姫路情報ITクリエイター法律専門学校",
        "address": "姫路市白銀町61",
        "lat": 34.831064,
        "lng": 134.691012
    },
    {
        "code": "H128310000762",
        "type": 16016,
        "name": "大原保育スポーツ医療専門学校姫路校",
        "address": "姫路市白銀町61",
        "lat": 34.831153,
        "lng": 134.691034
    },
    {
        "code": "H128310000824",
        "type": 16016,
        "name": "クラーク高等学院姫路校",
        "address": "姫路市東駅前町97",
        "lat": 34.829261,
        "lng": 134.693523
    },
    {
        "code": "H128310000833",
        "type": 16016,
        "name": "姫路医療専門学校",
        "address": "姫路市駅前町27-2",
        "lat": 34.826859,
        "lng": 134.694898
    },
    {
        "code": "H128310000879",
        "type": 16016,
        "name": "姫路医療センター附属看護学校",
        "address": "姫路市本町68",
        "lat": 34.838913,
        "lng": 134.698992
    },
    {
        "code": "H128310000888",
        "type": 16016,
        "name": "兵庫徳誠会歯科衛生士学校",
        "address": "姫路市高尾町87",
        "lat": 34.829195,
        "lng": 134.683928
    },
    {
        "code": "H228310000324",
        "type": 16015,
        "name": "兵庫県自動車学校姫路校",
        "address": "姫路市花田町一本松25",
        "lat": 34.823918,
        "lng": 134.72682
    },
    {
        "code": "H228310000333",
        "type": 16015,
        "name": "西播朝鮮初中級学校",
        "address": "姫路市苫編町60",
        "lat": 34.816381,
        "lng": 134.655903
    },
    {
        "code": "H228310000342",
        "type": 16015,
        "name": "姫路予備校",
        "address": "姫路市東延末1-108",
        "lat": 34.82437,
        "lng": 134.685102
    }
]