[
    {
        "code": "A103240200013",
        "type": 16011,
        "name": "平泉幼稚園",
        "address": "西磐井郡平泉町平泉字倉町152",
        "lat": 38.98606,
        "lng": 141.109956
    },
    {
        "code": "B103240200011",
        "type": 16001,
        "name": "平泉小学校",
        "address": "西磐井郡平泉町平泉字倉町155",
        "lat": 38.985951,
        "lng": 141.109289
    },
    {
        "code": "B103240200020",
        "type": 16001,
        "name": "長島小学校",
        "address": "西磐井郡平泉町長島字砂子沢33",
        "lat": 38.995395,
        "lng": 141.149285
    },
    {
        "code": "C103240200019",
        "type": 16002,
        "name": "平泉中学校",
        "address": "西磐井郡平泉町平泉字倉町23",
        "lat": 38.98484,
        "lng": 141.112066
    }
]