[
    {
        "code": "A104224450013",
        "type": 16011,
        "name": "賀美石幼稚園",
        "address": "加美郡加美町鳥屋ｹ崎字稲荷前183-1",
        "lat": 38.591368,
        "lng": 140.805991
    },
    {
        "code": "A104394450014",
        "type": 16011,
        "name": "小鳩幼稚園",
        "address": "加美郡加美町字矢越405",
        "lat": 38.575395,
        "lng": 140.858296
    },
    {
        "code": "A204224450012",
        "type": 16013,
        "name": "おのだひがし園",
        "address": "加美郡加美町字長檀26-3",
        "lat": 38.576269,
        "lng": 140.781306
    },
    {
        "code": "A204224450021",
        "type": 16013,
        "name": "おのだにし園",
        "address": "加美郡加美町字田中浦55",
        "lat": 38.589417,
        "lng": 140.730992
    },
    {
        "code": "A204224450030",
        "type": 16013,
        "name": "こども園みやざき園",
        "address": "加美郡加美町宮崎字屋敷1-6-2",
        "lat": 38.614913,
        "lng": 140.760931
    },
    {
        "code": "A204394450013",
        "type": 16013,
        "name": "中新田幼稚園・なかよしこども園",
        "address": "加美郡加美町字町裏451-1",
        "lat": 38.569071,
        "lng": 140.863697
    },
    {
        "code": "B104224450011",
        "type": 16001,
        "name": "中新田小学校",
        "address": "加美郡加美町字西田4-7-1",
        "lat": 38.570854,
        "lng": 140.854132
    },
    {
        "code": "B104224450020",
        "type": 16001,
        "name": "広原小学校",
        "address": "加美郡加美町上狼塚字東北原12-1",
        "lat": 38.595711,
        "lng": 140.86572
    },
    {
        "code": "B104224450039",
        "type": 16001,
        "name": "鳴瀬小学校",
        "address": "加美郡加美町四日市場字舟橋250",
        "lat": 38.557105,
        "lng": 140.878777
    },
    {
        "code": "B104224450048",
        "type": 16001,
        "name": "東小野田小学校",
        "address": "加美郡加美町字南寺宿45",
        "lat": 38.575988,
        "lng": 140.782952
    },
    {
        "code": "B104224450057",
        "type": 16001,
        "name": "鹿原小学校",
        "address": "加美郡加美町字鹿原水堀3-1",
        "lat": 38.567099,
        "lng": 140.744345
    },
    {
        "code": "B104224450066",
        "type": 16001,
        "name": "西小野田小学校",
        "address": "加美郡加美町字上野目高畑5",
        "lat": 38.588485,
        "lng": 140.731012
    },
    {
        "code": "B104224450075",
        "type": 16001,
        "name": "宮崎小学校",
        "address": "加美郡加美町宮崎字屋敷1-6-2",
        "lat": 38.615145,
        "lng": 140.75977
    },
    {
        "code": "B104224450084",
        "type": 16001,
        "name": "賀美石小学校",
        "address": "加美郡加美町鳥屋ヶ崎字神明127",
        "lat": 38.591265,
        "lng": 140.80295
    },
    {
        "code": "C104224450019",
        "type": 16002,
        "name": "中新田中学校",
        "address": "加美郡加美町字一本杉12",
        "lat": 38.570159,
        "lng": 140.865444
    },
    {
        "code": "C104224450028",
        "type": 16002,
        "name": "小野田中学校",
        "address": "加美郡加美町字中原23-41",
        "lat": 38.583209,
        "lng": 140.778786
    },
    {
        "code": "C104224450037",
        "type": 16002,
        "name": "宮崎中学校",
        "address": "加美郡加美町柳沢字桧葉野屋敷49",
        "lat": 38.602929,
        "lng": 140.772397
    },
    {
        "code": "D104214450018",
        "type": 16004,
        "name": "中新田高等学校",
        "address": "加美郡加美町字一本柳南28",
        "lat": 38.569048,
        "lng": 140.854056
    }
]