[
    {
        "code": "A205321320013",
        "type": 16013,
        "name": "認定こども園しゃろーむ",
        "address": "北秋田市東横町10-34",
        "lat": 40.224157,
        "lng": 140.370114
    },
    {
        "code": "B105221311015",
        "type": 16001,
        "name": "鷹巣小学校",
        "address": "北秋田市鷹巣字南中家下37-1",
        "lat": 40.222173,
        "lng": 140.363871
    },
    {
        "code": "B105221311024",
        "type": 16001,
        "name": "鷹巣東小学校",
        "address": "北秋田市栄字田沢古川布252",
        "lat": 40.234673,
        "lng": 140.390978
    },
    {
        "code": "B105221311033",
        "type": 16001,
        "name": "綴子小学校",
        "address": "北秋田市綴子字街道下59",
        "lat": 40.25467,
        "lng": 140.377367
    },
    {
        "code": "B105221311417",
        "type": 16001,
        "name": "米内沢小学校",
        "address": "北秋田市本城字中島1-2",
        "lat": 40.123512,
        "lng": 140.363191
    },
    {
        "code": "B105221311435",
        "type": 16001,
        "name": "前田小学校",
        "address": "北秋田市阿仁前田字下川端103-1",
        "lat": 40.065339,
        "lng": 140.412863
    },
    {
        "code": "B105221311514",
        "type": 16001,
        "name": "阿仁合小学校",
        "address": "北秋田市阿仁水無字上岱13-2",
        "lat": 40.006489,
        "lng": 140.402744
    },
    {
        "code": "B105221311603",
        "type": 16001,
        "name": "大阿仁小学校",
        "address": "北秋田市阿仁比立内字様ﾉ向1",
        "lat": 39.9075,
        "lng": 140.456796
    },
    {
        "code": "B105221311854",
        "type": 16001,
        "name": "合川小学校",
        "address": "北秋田市李岱字家向26-1",
        "lat": 40.158226,
        "lng": 140.314782
    },
    {
        "code": "B105221319534",
        "type": 16001,
        "name": "清鷹小学校",
        "address": "北秋田市脇神字塚ﾉ岱165-1",
        "lat": 40.206182,
        "lng": 140.392588
    },
    {
        "code": "C105221341017",
        "type": 16002,
        "name": "鷹巣中学校",
        "address": "北秋田市坊沢字下上野79",
        "lat": 40.234949,
        "lng": 140.358203
    },
    {
        "code": "C105221341231",
        "type": 16002,
        "name": "森吉中学校",
        "address": "北秋田市桂瀬字下柏木岱1",
        "lat": 40.099924,
        "lng": 140.419828
    },
    {
        "code": "C105221341339",
        "type": 16002,
        "name": "阿仁中学校",
        "address": "北秋田市阿仁水無字畑町東裏194",
        "lat": 39.995069,
        "lng": 140.405432
    },
    {
        "code": "C105221341516",
        "type": 16002,
        "name": "合川中学校",
        "address": "北秋田市李岱字家向1",
        "lat": 40.158422,
        "lng": 140.314561
    },
    {
        "code": "D105221355303",
        "type": 16004,
        "name": "秋田北鷹高等学校",
        "address": "北秋田市伊勢町1-1",
        "lat": 40.225342,
        "lng": 140.376613
    },
    {
        "code": "E105221399175",
        "type": 16012,
        "name": "比内支援学校たかのす校",
        "address": "北秋田市七日市字家向49の内",
        "lat": 40.156904,
        "lng": 140.398759
    }
]